aicosmodelzoo/__init__.py
aicosmodelzoo/aicosmodelzoo.py
aicosmodelzoo-0.0.8.dist-info/METADATA
aicosmodelzoo-0.0.8.dist-info/WHEEL
aicosmodelzoo-0.0.8.dist-info/top_level.txt
aicosmodelzoo-0.0.8.dist-info/RECORD
